htdb.cp310-win_amd64.pyd
htdb_py-0.5.0.dist-info/LICENSE
htdb_py-0.5.0.dist-info/METADATA
htdb_py-0.5.0.dist-info/WHEEL
htdb_py-0.5.0.dist-info/top_level.txt
htdb_py-0.5.0.dist-info/RECORD
