Metadata-Version: 2.1
Name: htdb-py
Version: 0.5.0
Requires-Python: >=3.9
License-File: LICENSE
Provides-Extra: test
Requires-Dist: pytest ; extra == 'test'
